bioimagekit/__init__.py
bioimagekit-0.0.0.dist-info/licenses/LICENSE
bioimagekit-0.0.0.dist-info/METADATA
bioimagekit-0.0.0.dist-info/WHEEL
bioimagekit-0.0.0.dist-info/top_level.txt
bioimagekit-0.0.0.dist-info/RECORD
