Metadata-Version: 2.4
Name: bioimagekit
Version: 0.0.0
Summary: A toolkit for bioimage processing in Python
Author: Ira Novianti
License: MIT
Project-URL: Homepage, https://github.com/iranovianti/bioimagekit
Classifier: Development Status :: 1 - Planning
Classifier: License :: OSI Approved :: MIT License
Classifier: Programming Language :: Python :: 3
Classifier: Operating System :: OS Independent
Requires-Python: >=3.7
License-File: LICENSE
Dynamic: license-file
